AUTHORS.rst
CONTRIBUTING.rst
HISTORY.rst
LICENSE
MANIFEST.in
README.rst
requirements.txt
setup.cfg
setup.py
test_requirements.txt
lib/astunparse_noparen/__init__.py
lib/astunparse_noparen/__main__.py
lib/astunparse_noparen/printer.py
lib/astunparse_noparen/unparser.py
lib/astunparse_noparen.egg-info/PKG-INFO
lib/astunparse_noparen.egg-info/SOURCES.txt
lib/astunparse_noparen.egg-info/dependency_links.txt
lib/astunparse_noparen.egg-info/not-zip-safe
lib/astunparse_noparen.egg-info/requires.txt
lib/astunparse_noparen.egg-info/top_level.txt